venvwatch/__init__.py
venvwatch/cli.py
venvwatch/core.py
venvwatch/main.py
venvwatch/utils.py
venvwatch-0.6.dist-info/LICENSE
venvwatch-0.6.dist-info/METADATA
venvwatch-0.6.dist-info/WHEEL
venvwatch-0.6.dist-info/entry_points.txt
venvwatch-0.6.dist-info/top_level.txt
venvwatch-0.6.dist-info/RECORD
