Metadata-Version: 2.1
Name: venvwatch
Version: 0.6
Summary: Automatically updates requirements.txt by watching your virtual environment for changes
Author: Casual Engineer Zombie
Author-email: py@casualzom.dev
Project-URL: Source, https://github.com/CasualEngineerZombie/venvwatch
Project-URL: Tracker, https://github.com/CasualEngineerZombie/venvwatch/issues
Classifier: Programming Language :: Python :: 3
Classifier: License :: OSI Approved :: MIT License
Classifier: Operating System :: OS Independent
License-File: LICENSE
Requires-Dist: watchdog
